flask_uploader/__init__.py
flask_uploader/core.py
flask_uploader/exceptions.py
flask_uploader/formats.py
flask_uploader/py.typed
flask_uploader/storages.py
flask_uploader/typing.py
flask_uploader/utils.py
flask_uploader/validators.py
flask_uploader/views.py
flask_uploader/contrib/__init__.py
flask_uploader/contrib/aws.py
flask_uploader/contrib/pymongo.py
flask_uploader/contrib/wtf.py
Flask_Uploader-0.3.1.dist-info/LICENSE
Flask_Uploader-0.3.1.dist-info/METADATA
Flask_Uploader-0.3.1.dist-info/WHEEL
Flask_Uploader-0.3.1.dist-info/top_level.txt
Flask_Uploader-0.3.1.dist-info/RECORD
