Metadata-Version: 2.1
Name: Flask-Uploader
Version: 0.3.1
Summary: File uploader for Flask with flexible extensibility.
Author-email: Kirill Vercetti <office@kyzima-spb.com>
License: MIT License
Project-URL: Homepage, https://github.com/kyzima-spb/flask-uploader
Project-URL: Repository, https://github.com/kyzima-spb/flask-uploader.git
Project-URL: Issue Tracker, https://github.com/kyzima-spb/flask-uploader/issues
Project-URL: Change log, https://github.com/kyzima-spb/flask-uploader#flask-uploader
Keywords: flask,flask upload,flask upload files,file uploader,flask aws s3
Classifier: Development Status :: 4 - Beta
Classifier: Environment :: Web Environment
Classifier: Framework :: Flask
Classifier: Intended Audience :: Developers
Classifier: Operating System :: OS Independent
Classifier: Programming Language :: Python
Classifier: Topic :: Internet :: WWW/HTTP :: Dynamic Content
Requires-Python: >=3.7
License-File: LICENSE
Requires-Dist: flask >=0.11
Requires-Dist: Flask-WTF >=0.13
Requires-Dist: Pillow >=8.0
Requires-Dist: importlib-metadata ; python_version < "3.8"
Requires-Dist: typing-extensions ; python_version < "3.9"
Provides-Extra: aws
Requires-Dist: boto3 >=1.22 ; extra == 'aws'
Provides-Extra: dev
Requires-Dist: pytest >=7.1 ; extra == 'dev'
Requires-Dist: pytest-mock >=3.7 ; extra == 'dev'
Requires-Dist: flake8 >=4 ; extra == 'dev'
Requires-Dist: boto3-stubs-lite[s3] ; extra == 'dev'
Requires-Dist: mypy >=0.950 ; extra == 'dev'
Requires-Dist: types-pillow ; extra == 'dev'
Provides-Extra: pymongo
Requires-Dist: flask-pymongo >=2.3 ; extra == 'pymongo'
